[{
    "id":"1000",
    "name":"index.html",
    "path":"index.html",
    "type":"file",
    "last_modified_time":"1463476530000",
    "parent":""
},
{
    "id":"1001",
    "name":"about.html",
    "path":"about.html",
    "type":"file",
    "last_modified_time":"1453496531000",
    "parent":""
},
{
    "id":"1002",
    "name":"files",
    "path":"files",
    "type":"folder",
    "last_modified_time":"1453496531000",
    "parent":""
},
{
    "id":"1003",
    "name":"test.html",
    "path":"/files/test.html",
    "type":"file",
    "last_modified_time":"1453496531000",
    "parent":"1002"
}]